[
  {
    "ProductName": "TRAMADOL HYDROCHLORIDE",
    "Price": 516.48,
    "FullName": "Cunningham"
  },
  {
    "ProductName": "Allopurinol",
    "Price": 518.50,
    "FullName": "Jeremy Woods"
  },
  {
    "ProductName": "Parsley",
    "Price": 519.06,
    "FullName": "Sarah Day"
  },
  {
    "ProductName": "equaline",
    "Price": 520.45,
    "FullName": "Eugene Stewart"
  },
  {
    "ProductName": "Extra Strength Pain Reliever PM",
    "Price": 542.72,
    "FullName": "Cunningham"
  },
  {
    "ProductName": "Propranolol Hydrochloride",
    "Price": 546.95,
    "FullName": "Paula Hill"
  },
  {
    "ProductName": "Prednisone",
    "Price": 550.72,
    "FullName": "Fred Allen"
  },
  {
    "ProductName": "TERSI",
    "Price": 554.91,
    "FullName": "Chris Mitchell"
  },
  {
    "ProductName": "DAYWEAR PLUS MULTI PROTECTION TINTED MOISTURIZER",
    "Price": 555.12,
    "FullName": "Carl Daniels"
  },
  {
    "ProductName": "PLANTAGO LANCEOLATA POLLEN",
    "Price": 561.68,
    "FullName": "Fred Allen"
  },
  {
    "ProductName": "Echinacea Quartz Gum Support",
    "Price": 570.08,
    "FullName": "Betty Lawson"
  },
  {
    "ProductName": "Topiramate",
    "Price": 578.77,
    "FullName": "Clarence Fowler"
  },
  {
    "ProductName": "AIR",
    "Price": 581.69,
    "FullName": "Billy Parker"
  },
  {
    "ProductName": "Agaricus Equisetum Special Order",
    "Price": 585.93,
    "FullName": "Paula Hill"
  },
  {
    "ProductName": "Gemcitabine",
    "Price": 594.79,
    "FullName": "Paula Hill"
  },
  {
    "ProductName": "Ketorolac Tromethamine",
    "Price": 608.18,
    "FullName": "Anna Parker"
  },
  {
    "ProductName": "Pleo Ginkgo",
    "Price": 613.65,
    "FullName": "Paula Hill"
  },
  {
    "ProductName": "Diastat",
    "Price": 614.14,
    "FullName": "Jacqueline Perez"
  },
  {
    "ProductName": "No7 Protect and Perfect Foundation Sunscreen Broad Spectrum SPF 15 Cool Ivory",
    "Price": 616.19,
    "FullName": "Diana Harvey"
  },
  {
    "ProductName": "Glipizide",
    "Price": 621.78,
    "FullName": "Joshua Murray"
  },
  {
    "ProductName": "AMARANTHUS PALMERI POLLEN",
    "Price": 623.16,
    "FullName": "Kathy Gilbert"
  },
  {
    "ProductName": "Foaming Hand Sanitizer",
    "Price": 624.72,
    "FullName": "Bonnie Fox"
  },
  {
    "ProductName": "ziprasidone hydrochloride",
    "Price": 628.66,
    "FullName": "Cunningham"
  },
  {
    "ProductName": "AVANDAMET",
    "Price": 632.08,
    "FullName": "Paula Hill"
  },
  {
    "ProductName": "Imipramine Hydrochloride",
    "Price": 648.69,
    "FullName": "Sarah Day"
  },
  {
    "ProductName": "Childrens Allegra Allergy",
    "Price": 650.97,
    "FullName": "Sarah Day"
  },
  {
    "ProductName": "Strattera",
    "Price": 658.54,
    "FullName": "Amanda Frazier"
  },
  {
    "ProductName": "Amitiza",
    "Price": 666.58,
    "FullName": "Amanda Frazier"
  },
  {
    "ProductName": "ENBREL",
    "Price": 673.97,
    "FullName": "Carl Daniels"
  },
  {
    "ProductName": "Ampicillin",
    "Price": 674.63,
    "FullName": "Carl Daniels"
  },
  {
    "ProductName": "PRIMAXIN",
    "Price": 686.66,
    "FullName": "Betty Ward"
  },
  {
    "ProductName": "CLARINS Ever Matte SPF 15 - 105 Nude",
    "Price": 696.06,
    "FullName": "Marie Williamson"
  },
  {
    "ProductName": "CALMING DIAPER RASH",
    "Price": 700.92,
    "FullName": "Fred Allen"
  },
  {
    "ProductName": "Acnezzol Base",
    "Price": 710.60,
    "FullName": "Fred Allen"
  },
  {
    "ProductName": "Prostate",
    "Price": 716.05,
    "FullName": "Billy Parker"
  },
  {
    "ProductName": "Pleo Lat",
    "Price": 720.08,
    "FullName": "Jacqueline Perez"
  },
  {
    "ProductName": "GOONG SECRET CALMING BATH",
    "Price": 742.47,
    "FullName": "Christina Patterson"
  },
  {
    "ProductName": "Warfarin Sodium",
    "Price": 770.05,
    "FullName": "Billy Parker"
  },
  {
    "ProductName": "Pollens - Weeds and Garden Plants, Nettle Urtica dioica",
    "Price": 782.77,
    "FullName": "Arthur Reynolds"
  },
  {
    "ProductName": "Isosorbide Mononitrate",
    "Price": 789.91,
    "FullName": "Chris Mitchell"
  },
  {
    "ProductName": "Naproxen",
    "Price": 807.22,
    "FullName": "Thompson"
  },
  {
    "ProductName": "Meloxicam",
    "Price": 809.18,
    "FullName": "Jean Henry"
  },
  {
    "ProductName": "Clarins Paris Skin Illusion - 114 cappuccino",
    "Price": 811.42,
    "FullName": "Kathy Gilbert"
  },
  {
    "ProductName": "Azithromycin",
    "Price": 813.87,
    "FullName": "Kathy Gilbert"
  },
  {
    "ProductName": "LV-FX",
    "Price": 820.87,
    "FullName": "Betty Lawson"
  },
  {
    "ProductName": "IOPE SUPER VITAL",
    "Price": 824.68,
    "FullName": "Christine Gomez"
  },
  {
    "ProductName": "Aquafresh",
    "Price": 849.93,
    "FullName": "Patricia Cooper"
  },
  {
    "ProductName": "RESCRIPTOR",
    "Price": 850.52,
    "FullName": "Betty Lawson"
  },
  {
    "ProductName": "Moore Medical Sinus Pain and Pressure Relief",
    "Price": 855.39,
    "FullName": "Betty Lawson"
  },
  {
    "ProductName": "Shopko Lip Treatment",
    "Price": 861.42,
    "FullName": "Thomas Snyder"
  },
  {
    "ProductName": "Perrigo Benzoyl Peroxide",
    "Price": 873.24,
    "FullName": "Thomas Snyder"
  },
  {
    "ProductName": "ESIKA",
    "Price": 879.37,
    "FullName": "Clarence Fowler"
  },
  {
    "ProductName": "Levothyroxine Sodium",
    "Price": 885.86,
    "FullName": "Jeremy Woods"
  },
  {
    "ProductName": "EPZICOM",
    "Price": 895.65,
    "FullName": "Fred Allen"
  },
  {
    "ProductName": "Myristica Argentum Sinus Relief",
    "Price": 904.52,
    "FullName": "Jacqueline Perez"
  },
  {
    "ProductName": "Aspirin",
    "Price": 925.45,
    "FullName": "Bonnie Fox"
  },
  {
    "ProductName": "Ranitidine",
    "Price": 926.64,
    "FullName": "Joshua Murray"
  },
  {
    "ProductName": "Care One Hemorrhoidal",
    "Price": 932.18,
    "FullName": "Eugene Stewart"
  },
  {
    "ProductName": "Spironolactone",
    "Price": 933.69,
    "FullName": "Paula Hill"
  },
  {
    "ProductName": "pain relief",
    "Price": 938.23,
    "FullName": "Jacqueline Perez"
  },
  {
    "ProductName": "Glipizide and Metformin Hydrochloride",
    "Price": 953.60,
    "FullName": "Jennifer Riley"
  },
  {
    "ProductName": "Metformin Hydrochloride",
    "Price": 953.99,
    "FullName": "Patricia Cooper"
  },
  {
    "ProductName": "Homeopathic Rheumatism",
    "Price": 967.08,
    "FullName": "Paula Hill"
  },
  {
    "ProductName": "NEO-POLY-BAC HYDRO",
    "Price": 967.32,
    "FullName": "Christine Gomez"
  },
  {
    "ProductName": "Clearskin",
    "Price": 968.59,
    "FullName": "Chris Mitchell"
  },
  {
    "ProductName": "Dawn Ultra Antibacterial Hand",
    "Price": 969.86,
    "FullName": "Emily Parker"
  },
  {
    "ProductName": "Megestrol Acetate",
    "Price": 976.15,
    "FullName": "Carl Daniels"
  },
  {
    "ProductName": "Smooth texture Orange flavor",
    "Price": 976.65,
    "FullName": "Patricia Fuller"
  },
  {
    "ProductName": "Retin-A MICRO",
    "Price": 995.98,
    "FullName": "Bonnie Fox"
  }
]